TracRobotsTxt-2.1.dist-info/DESCRIPTION.rst
TracRobotsTxt-2.1.dist-info/METADATA
TracRobotsTxt-2.1.dist-info/RECORD
TracRobotsTxt-2.1.dist-info/WHEEL
TracRobotsTxt-2.1.dist-info/entry_points.txt
TracRobotsTxt-2.1.dist-info/metadata.json
TracRobotsTxt-2.1.dist-info/top_level.txt
robotstxt/__init__.py
robotstxt/web_ui.py
