Metadata-Version: 2.0
Name: TracRobotsTxt
Version: 2.1
Summary: Serve a robots.txt file from Trac.
Home-page: http://trac-hacks.org/wiki/RobotsTxtPlugin
Author: Noah Kantrowitz
Author-email: noah@coderanger.net
License: 3-Clause BSD
Download-URL: http://trac-hacks.org/svn/robotstxtplugin/0.11#egg=TracRobotsTxt-dev
Keywords: trac plugin robots
Platform: UNKNOWN
Classifier: Framework :: Trac
Classifier: Development Status :: 6 - Mature
Classifier: Environment :: Web Environment
Classifier: License :: OSI Approved :: BSD License
Classifier: Natural Language :: English
Classifier: Operating System :: OS Independent
Requires-Dist: Trac
